LICENSE
MANIFEST.in
README.md
package.json
setup.py
dash_alert/DashAlert.py
dash_alert/__init__.py
dash_alert/_imports_.py
dash_alert/dash_alert.min.js
dash_alert/dash_alert.min.js.map
dash_alert/metadata.json
dash_alert/package-info.json
dash_alert.egg-info/PKG-INFO
dash_alert.egg-info/SOURCES.txt
dash_alert.egg-info/dependency_links.txt
dash_alert.egg-info/top_level.txt