Metadata-Version: 2.1
Name: dash-alert
Version: 1.0.8
Summary: Alert component for Dash
Author: s_matsumoto <s_matsumoto@thinkup-sol.co.jp>
License: MIT
Classifier: Framework :: Dash
License-File: LICENSE
